redbot/__init__.py
redbot/__main__.py
redbot/launcher.py
redbot/logging.py
redbot/meta.py
redbot/py.typed
redbot/setup.py
redbot/cogs/__init__.py
redbot/cogs/admin/__init__.py
redbot/cogs/admin/admin.py
redbot/cogs/admin/announcer.py
redbot/cogs/admin/converters.py
redbot/cogs/admin/locales/en-PT.po
redbot/cogs/alias/__init__.py
redbot/cogs/alias/alias.py
redbot/cogs/alias/alias_entry.py
redbot/cogs/alias/locales/en-PT.po
redbot/cogs/audio/__init__.py
redbot/cogs/audio/audio_dataclasses.py
redbot/cogs/audio/audio_logging.py
redbot/cogs/audio/converters.py
redbot/cogs/audio/equalizer.py
redbot/cogs/audio/errors.py
redbot/cogs/audio/manager.py
redbot/cogs/audio/sql_statements.py
redbot/cogs/audio/utils.py
redbot/cogs/audio/apis/__init__.py
redbot/cogs/audio/apis/api_utils.py
redbot/cogs/audio/apis/global_db.py
redbot/cogs/audio/apis/interface.py
redbot/cogs/audio/apis/local_db.py
redbot/cogs/audio/apis/playlist_interface.py
redbot/cogs/audio/apis/playlist_wrapper.py
redbot/cogs/audio/apis/spotify.py
redbot/cogs/audio/apis/youtube.py
redbot/cogs/audio/core/__init__.py
redbot/cogs/audio/core/abc.py
redbot/cogs/audio/core/cog_utils.py
redbot/cogs/audio/core/commands/__init__.py
redbot/cogs/audio/core/commands/audioset.py
redbot/cogs/audio/core/commands/controller.py
redbot/cogs/audio/core/commands/equalizer.py
redbot/cogs/audio/core/commands/llset.py
redbot/cogs/audio/core/commands/localtracks.py
redbot/cogs/audio/core/commands/miscellaneous.py
redbot/cogs/audio/core/commands/player.py
redbot/cogs/audio/core/commands/playlists.py
redbot/cogs/audio/core/commands/queue.py
redbot/cogs/audio/core/events/__init__.py
redbot/cogs/audio/core/events/cog.py
redbot/cogs/audio/core/events/dpy.py
redbot/cogs/audio/core/events/lavalink.py
redbot/cogs/audio/core/events/red.py
redbot/cogs/audio/core/tasks/__init__.py
redbot/cogs/audio/core/tasks/lavalink.py
redbot/cogs/audio/core/tasks/player.py
redbot/cogs/audio/core/tasks/startup.py
redbot/cogs/audio/core/utilities/__init__.py
Kr0nOs_Bot-3.3.11.dist-info/LICENSE
Kr0nOs_Bot-3.3.11.dist-info/METADATA
Kr0nOs_Bot-3.3.11.dist-info/WHEEL
Kr0nOs_Bot-3.3.11.dist-info/entry_points.txt
Kr0nOs_Bot-3.3.11.dist-info/top_level.txt
Kr0nOs_Bot-3.3.11.dist-info/RECORD
