Metadata-Version: 2.1
Name: Kr0nOs-Bot
Version: 3.3.11
Summary: A highly customisable Discord bot
Home-page: https://github.com/KableKompany/Kr0nOs-Core
Author: KableKompany
Author-email: trent@kablekompany.com
License: GPL-3.0
Platform: UNKNOWN
Classifier: Development Status :: 5 - Production/Stable
Classifier: Framework :: AsyncIO
Classifier: Framework :: Pytest
Classifier: Intended Audience :: Developers
Classifier: Intended Audience :: End Users/Desktop
Classifier: License :: OSI Approved :: GNU General Public License v3 (GPLv3)
Classifier: Natural Language :: English
Classifier: Operating System :: OS Independent
Classifier: Programming Language :: Python :: 3.8
Classifier: Topic :: Communications :: Chat
Classifier: Topic :: Documentation :: Sphinx
Requires-Python: >=3.8.1
Requires-Dist: aiohttp (==3.6.2)
Requires-Dist: aiohttp-json-rpc (==0.12.3)
Requires-Dist: aiosqlite (==0.11.0)
Requires-Dist: appdirs (==1.4.3)
Requires-Dist: apsw-wheels (==3.30.1.post3)
Requires-Dist: async-timeout (==3.0.1)
Requires-Dist: attrs (==19.3.0)
Requires-Dist: Babel (==2.8.0)
Requires-Dist: chardet (==3.0.4)
Requires-Dist: click (==7.1.1)
Requires-Dist: colorama (==0.4.3)
Requires-Dist: contextlib2 (==0.5.5)
Requires-Dist: discord.py (==1.3.3)
Requires-Dist: fuzzywuzzy (==0.18.0)
Requires-Dist: idna (==2.9)
Requires-Dist: multidict (==4.7.5)
Requires-Dist: python-Levenshtein-wheels (==0.13.1)
Requires-Dist: pytz (==2019.3)
Requires-Dist: PyYAML (==5.3.1)
Requires-Dist: Red-Lavalink (==0.5.1)
Requires-Dist: schema (==0.7.1)
Requires-Dist: tqdm (==4.45.0)
Requires-Dist: websockets (==8.1)
Requires-Dist: yarl (==1.4.2)
Requires-Dist: uvloop (==0.14.0) ; sys_platform != "win32" and platform_python_implementation == "CPython"
Requires-Dist: distro (==1.5.0) ; sys_platform == "linux"
Provides-Extra: docs
Requires-Dist: alabaster (==0.7.12) ; extra == 'docs'
Requires-Dist: certifi (==2019.11.28) ; extra == 'docs'
Requires-Dist: docutils (==0.16) ; extra == 'docs'
Requires-Dist: imagesize (==1.2.0) ; extra == 'docs'
Requires-Dist: Jinja2 (==2.11.1) ; extra == 'docs'
Requires-Dist: MarkupSafe (==1.1.1) ; extra == 'docs'
Requires-Dist: packaging (==20.3) ; extra == 'docs'
Requires-Dist: Pygments (==2.6.1) ; extra == 'docs'
Requires-Dist: pyparsing (==2.4.6) ; extra == 'docs'
Requires-Dist: requests (==2.23.0) ; extra == 'docs'
Requires-Dist: six (==1.14.0) ; extra == 'docs'
Requires-Dist: snowballstemmer (==2.0.0) ; extra == 'docs'
Requires-Dist: Sphinx (==2.4.4) ; extra == 'docs'
Requires-Dist: sphinx-rtd-theme (==0.4.3) ; extra == 'docs'
Requires-Dist: sphinxcontrib-applehelp (==1.0.2) ; extra == 'docs'
Requires-Dist: sphinxcontrib-devhelp (==1.0.2) ; extra == 'docs'
Requires-Dist: sphinxcontrib-htmlhelp (==1.0.3) ; extra == 'docs'
Requires-Dist: sphinxcontrib-jsmath (==1.0.1) ; extra == 'docs'
Requires-Dist: sphinxcontrib-qthelp (==1.0.3) ; extra == 'docs'
Requires-Dist: sphinxcontrib-serializinghtml (==1.1.4) ; extra == 'docs'
Requires-Dist: sphinxcontrib-trio (==1.1.1) ; extra == 'docs'
Requires-Dist: urllib3 (==1.25.8) ; extra == 'docs'
Provides-Extra: postgres
Requires-Dist: asyncpg (==0.20.1) ; extra == 'postgres'
Provides-Extra: style
Requires-Dist: black (==19.10b0) ; extra == 'style'
Requires-Dist: pathspec (==0.7.0) ; extra == 'style'
Requires-Dist: regex (==2020.4.4) ; extra == 'style'
Requires-Dist: toml (==0.10.0) ; extra == 'style'
Requires-Dist: typed-ast (==1.4.1) ; extra == 'style'
Provides-Extra: test
Requires-Dist: astroid (==2.3.3) ; extra == 'test'
Requires-Dist: isort (==4.3.21) ; extra == 'test'
Requires-Dist: lazy-object-proxy (==1.4.3) ; extra == 'test'
Requires-Dist: mccabe (==0.6.1) ; extra == 'test'
Requires-Dist: more-itertools (==8.2.0) ; extra == 'test'
Requires-Dist: packaging (==20.3) ; extra == 'test'
Requires-Dist: pluggy (==0.13.1) ; extra == 'test'
Requires-Dist: py (==1.8.1) ; extra == 'test'
Requires-Dist: pylint (==2.4.4) ; extra == 'test'
Requires-Dist: pyparsing (==2.4.6) ; extra == 'test'
Requires-Dist: pytest (==5.4.1) ; extra == 'test'
Requires-Dist: pytest-asyncio (==0.10.0) ; extra == 'test'
Requires-Dist: pytest-mock (==3.0.0) ; extra == 'test'
Requires-Dist: six (==1.14.0) ; extra == 'test'
Requires-Dist: wcwidth (==0.1.9) ; extra == 'test'
Requires-Dist: wrapt (==1.11.2) ; extra == 'test'
